{
	"name": "Pipeline data flow dynamic",
	"properties": {
		"activities": [
			{
				"name": "Data flow1",
				"type": "ExecuteDataFlow",
				"dependsOn": [],
				"policy": {
					"timeout": "0.12:00:00",
					"retry": 0,
					"retryIntervalInSeconds": 30,
					"secureOutput": false,
					"secureInput": false
				},
				"userProperties": [],
				"typeProperties": {
					"dataflow": {
						"referenceName": "Dataflow4",
						"type": "DataFlowReference",
						"datasetParameters": {
							"source1": {
								"SheetIndex": {
									"value": "@pipeline().parameters.SoureSheetName",
									"type": "Expression"
								}
							},
							"sink1": {
								"CSVName": {
									"value": "@pipeline().parameters.SinkSheetName",
									"type": "Expression"
								}
							}
						}
					},
					"compute": {
						"coreCount": 8,
						"computeType": "General"
					},
					"traceLevel": "Fine"
				}
			}
		],
		"parameters": {
			"SoureFileName": {
				"type": "string"
			},
			"SoureSheetName": {
				"type": "string",
				"defaultValue": "5.1"
			},
			"SinkFileName": {
				"type": "string"
			},
			"SinkSheetName": {
				"type": "string",
				"defaultValue": "5.1"
			}
		},
		"annotations": []
	}
}